psychosnd/__about__.py
psychosnd/__init__.py
psychosnd/__main__.py
psychosnd/psychcsv.py
psychosnd/scla.py
psychosnd-0.0.9.dist-info/LICENSE.md
psychosnd-0.0.9.dist-info/METADATA
psychosnd-0.0.9.dist-info/WHEEL
psychosnd-0.0.9.dist-info/entry_points.txt
psychosnd-0.0.9.dist-info/top_level.txt
psychosnd-0.0.9.dist-info/RECORD
