Metadata-Version: 2.1
Name: psychosnd
Version: 0.0.9
Summary: Psychopy sound analysis scripts
Home-page: https://github.com/gjcooper/psychosnd
Author: Gavin Cooper
Author-email: gjcooper@gmail.com
License: GPLv3
Keywords: Psychopy,logfile,sound
Platform: UNKNOWN
Classifier: Development Status :: 3 - Alpha
Classifier: Intended Audience :: Developers
Classifier: Programming Language :: Python :: 3
Requires-Dist: cycler (==0.10.0)
Requires-Dist: fonttools (==4.28.3)
Requires-Dist: kiwisolver (==1.3.2)
Requires-Dist: matplotlib (==3.5.0)
Requires-Dist: numpy (==1.21.4)
Requires-Dist: packaging (==21.3)
Requires-Dist: pillow (==8.4.0)
Requires-Dist: prespy (==0.0.12)
Requires-Dist: pyparsing (==3.0.6)
Requires-Dist: python-dateutil (==2.8.2)
Requires-Dist: scipy (==1.7.3)
Requires-Dist: setuptools-scm (==6.3.2)
Requires-Dist: six (==1.10.0)
Requires-Dist: tomli (==1.2.2)
